freeclimb/__init__.py
freeclimb/api_client.py
freeclimb/api_response.py
freeclimb/configuration.py
freeclimb/exceptions.py
freeclimb/model_utils.py
freeclimb/py.typed
freeclimb/rest.py
freeclimb/api/__init__.py
freeclimb/api/default_api.py
freeclimb/models/__init__.py
freeclimb/models/account_request.py
freeclimb/models/account_result.py
freeclimb/models/account_status.py
freeclimb/models/account_type.py
freeclimb/models/add_to_conference.py
freeclimb/models/add_to_conference_notification_webhook.py
freeclimb/models/add_to_queue_notification_webhook.py
freeclimb/models/answered_by.py
freeclimb/models/application_list.py
freeclimb/models/application_request.py
freeclimb/models/application_result.py
freeclimb/models/available_number.py
freeclimb/models/available_number_list.py
freeclimb/models/barge_in_reason.py
freeclimb/models/buy_incoming_number_request.py
freeclimb/models/call_control_webhook.py
freeclimb/models/call_direction.py
freeclimb/models/call_ended_reason.py
freeclimb/models/call_list.py
freeclimb/models/call_result.py
freeclimb/models/call_status.py
freeclimb/models/call_status_webhook.py
freeclimb/models/capabilities.py
freeclimb/models/completion_request.py
freeclimb/models/completion_result.py
freeclimb/models/completion_result_status.py
freeclimb/models/conference_list.py
freeclimb/models/conference_participant_list.py
freeclimb/models/conference_participant_result.py
freeclimb/models/conference_recording_status_webhook.py
freeclimb/models/conference_result.py
freeclimb/models/conference_status.py
freeclimb/models/conference_status_webhook.py
freeclimb/models/create_conference.py
freeclimb/models/create_conference_request.py
freeclimb/models/create_conference_webhook.py
freeclimb/models/create_web_rtc_token.py
freeclimb/models/dequeue.py
freeclimb/models/dequeue_webhook.py
freeclimb/models/enqueue.py
freeclimb/models/export_list.py
freeclimb/models/export_output_type.py
freeclimb/models/export_request.py
freeclimb/models/export_request_output.py
freeclimb-5.2.0.dist-info/licenses/LICENSE.txt
freeclimb-5.2.0.dist-info/METADATA
freeclimb-5.2.0.dist-info/WHEEL
freeclimb-5.2.0.dist-info/top_level.txt
freeclimb-5.2.0.dist-info/RECORD
