Metadata-Version: 2.4
Name: FreeClimb
Version: 5.2.0
Summary: FreeClimb API
Home-page: https://freeclimb.com
Author: FreeClimb API Support
Author-email: support@freeclimb.com
Keywords: OpenAPI,OpenAPI-Generator,FreeClimb API
License-File: LICENSE.txt
Requires-Dist: urllib3<3.0.0,>=1.25.3
Requires-Dist: python-dateutil>=2.8.2
Requires-Dist: pydantic>=2
Requires-Dist: typing-extensions>=4.7.1
Dynamic: author
Dynamic: author-email
Dynamic: description
Dynamic: description-content-type
Dynamic: home-page
Dynamic: keywords
Dynamic: license-file
Dynamic: requires-dist
Dynamic: summary
